walterize/__init__.py
walterize/algorithm.py
walterize/cli.py
walterize-0.0.3.dist-info/LICENSE
walterize-0.0.3.dist-info/METADATA
walterize-0.0.3.dist-info/WHEEL
walterize-0.0.3.dist-info/entry_points.txt
walterize-0.0.3.dist-info/top_level.txt
walterize-0.0.3.dist-info/RECORD
